BrainML/__init__.py
BrainML/activation.py
BrainML/layers.py
BrainML/optimizer.py
BrainML-0.0.3.dist-info/LICENSE.txt
BrainML-0.0.3.dist-info/METADATA
BrainML-0.0.3.dist-info/WHEEL
BrainML-0.0.3.dist-info/top_level.txt
BrainML-0.0.3.dist-info/RECORD
