Metadata-Version: 2.1
Name: BrainML
Version: 0.0.3
Summary: BrainML is a machine learning library capable of implementing neural networks.
Home-page: https://github.com/bogdan124/BrainML
Author: Bibina Bogdan
Author-email: bogdanbibina@gmail.com
License: Apache license 2.0
Download-URL: https://github.com/bogdan124/BrainML/archive/0.0.1.tar.gz
Keywords: MachineLearning,library,neural networks,deep-learning,artificial-intelligence,artificial-neural-networks
Platform: UNKNOWN
Classifier: Development Status :: 3 - Alpha
Classifier: Intended Audience :: Developers
Classifier: Topic :: Software Development :: Build Tools
Classifier: License :: OSI Approved :: Apache Software License
Classifier: Programming Language :: Python :: 3
Classifier: Programming Language :: Python :: 3.4
Classifier: Programming Language :: Python :: 3.5
Classifier: Programming Language :: Python :: 3.6
Requires-Dist: tensorflow (==2.0.0)
